str2port/__init__.py
str2port/__main__.py
str2port/common.py
str2port/core.py
str2port/iana.csv
str2port-0.1.1.dist-info/entry_points.txt
str2port-0.1.1.dist-info/LICENSE
str2port-0.1.1.dist-info/WHEEL
str2port-0.1.1.dist-info/METADATA
str2port-0.1.1.dist-info/RECORD
